cubed4th/FORTH.py
cubed4th/__init__.py
cubed4th/cli_FORTH.py
cubed4th/doc_FORTH.py
cubed4th/WORDS/F_CHAINS.py
cubed4th/WORDS/F_CONTROL.py
cubed4th/WORDS/F_CORE.py
cubed4th/WORDS/F_CURSES.py
cubed4th/WORDS/F_ECDSA.py
cubed4th/WORDS/F_HASHES.py
cubed4th/WORDS/F_HTTPS.py
cubed4th/WORDS/F_INPUT.py
cubed4th/WORDS/F_JSON.py
cubed4th/WORDS/F_MATH.py
cubed4th/WORDS/F_OBJECT.py
cubed4th/WORDS/F_OUTPUT.py
cubed4th/WORDS/F_REPL.py
cubed4th/WORDS/F_STACK.py
cubed4th/WORDS/F_UNICODE.py
cubed4th/WORDS/__init__.py
pdoc/__init__.py
pdoc/__main__.py
pdoc/_compat.py
pdoc/doc.py
pdoc/doc_ast.py
pdoc/doc_types.py
pdoc/docstrings.py
pdoc/extract.py
pdoc/render.py
pdoc/render_helpers.py
pdoc/search.py
pdoc/web.py
pdoc/markdown2/__init__.py
simplejson/__init__.py
simplejson/compat.py
simplejson/decoder.py
simplejson/encoder.py
simplejson/errors.py
simplejson/ordered_dict.py
simplejson/raw_json.py
simplejson/scanner.py
simplejson/tool.py
simplejson/tests/__init__.py
simplejson/tests/_cibw_runner.py
simplejson/tests/test_bigint_as_string.py
simplejson/tests/test_bitsize_int_as_string.py
simplejson/tests/test_check_circular.py
simplejson/tests/test_decimal.py
simplejson/tests/test_decode.py
simplejson/tests/test_default.py
simplejson/tests/test_dump.py
simplejson/tests/test_encode_basestring_ascii.py
simplejson/tests/test_encode_for_html.py
simplejson/tests/test_errors.py
simplejson/tests/test_fail.py
simplejson/tests/test_float.py
simplejson/tests/test_for_json.py
simplejson/tests/test_indent.py
simplejson/tests/test_item_sort_key.py
simplejson/tests/test_iterable.py
simplejson/tests/test_namedtuple.py
simplejson/tests/test_pass1.py
simplejson/tests/test_pass2.py
simplejson/tests/test_pass3.py
simplejson/tests/test_raw_json.py
simplejson/tests/test_recursion.py
simplejson/tests/test_scanstring.py
simplejson/tests/test_separators.py
simplejson/tests/test_speedups.py
simplejson/tests/test_str_subclass.py
simplejson/tests/test_subclass.py
simplejson/tests/test_tool.py
cubed4th-2.0.20221024.dist-info/LICENSE
cubed4th-2.0.20221024.dist-info/LICENSE.md
cubed4th-2.0.20221024.dist-info/METADATA
cubed4th-2.0.20221024.dist-info/WHEEL
cubed4th-2.0.20221024.dist-info/entry_points.txt
cubed4th-2.0.20221024.dist-info/top_level.txt
cubed4th-2.0.20221024.dist-info/RECORD
