Metadata-Version: 2.1
Name: cubed4th
Version: 2.0.20221024
Summary: : cubed4th 'PYTHON 'FORTH 'OOP + * 3 ^ ;
Home-page: https://github.com/sno-ware/cubed4th
Author: Scott McCallum <https://linkedin.com/in/scott-mccallum>
Author-email: Scott@Urbane.eMail
License: UNKNOWN
Platform: UNKNOWN
Classifier: License :: OSI Approved :: MIT License
Classifier: Development Status :: 5 - Production/Stable
Classifier: Environment :: Console
Classifier: Environment :: Console :: Curses
Classifier: Environment :: Win32 (MS Windows)
Classifier: Environment :: No Input/Output (Daemon)
Classifier: Operating System :: OS Independent
Classifier: Intended Audience :: Developers
Classifier: Intended Audience :: Science/Research
Classifier: Intended Audience :: End Users/Desktop
Classifier: Intended Audience :: System Administrators
Classifier: Natural Language :: English
Classifier: Programming Language :: Python :: 3
Classifier: Programming Language :: Python :: Implementation :: CPython
Classifier: Programming Language :: Python :: Implementation :: PyPy
Classifier: Programming Language :: SQL
Classifier: Programming Language :: Forth
Classifier: Topic :: Education
Classifier: Topic :: Multimedia
Classifier: Topic :: Internet
Classifier: Topic :: Software Development
Classifier: Topic :: Software Development :: Code Generators
Classifier: Topic :: Software Development :: Bug Tracking
Classifier: Topic :: Software Development :: Interpreters
Classifier: Topic :: Software Development :: Libraries
Classifier: Topic :: Software Development :: Pre-processors
Classifier: Topic :: Software Development :: User Interfaces
Classifier: Topic :: Software Development :: Version Control
Classifier: Topic :: System :: Software Distribution
Classifier: Topic :: Text Processing
Classifier: Topic :: Text Processing :: Markup :: Markdown
Requires-Python: >=3.7
